reductus/__init__.py
reductus/git_revision
reductus/rev.py
reductus/configurations/__init__.py
reductus/configurations/default.py
reductus/dataflow/__init__.py
reductus/dataflow/anno_exc.py
reductus/dataflow/automod.py
reductus/dataflow/cache.py
reductus/dataflow/calc.py
reductus/dataflow/configure.py
reductus/dataflow/core.py
reductus/dataflow/data.py
reductus/dataflow/deps.py
reductus/dataflow/doi_resolve.py
reductus/dataflow/fakeredis.py
reductus/dataflow/fetch.py
reductus/dataflow/rst2html.py
reductus/dataflow/store.py
reductus/dataflow/subroutine_schema.json
reductus/dataflow/lib/__init__.py
reductus/dataflow/lib/err1d.py
reductus/dataflow/lib/errutil.py
reductus/dataflow/lib/exporters.py
reductus/dataflow/lib/formatnum.py
reductus/dataflow/lib/h5_open.py
reductus/dataflow/lib/hzf_readonly_stripped.py
reductus/dataflow/lib/iso8601.py
reductus/dataflow/lib/octave.py
reductus/dataflow/lib/rebin.py
reductus/dataflow/lib/seed.py
reductus/dataflow/lib/strings.py
reductus/dataflow/lib/uncertainty.py
reductus/dataflow/lib/unit.py
reductus/dataflow/lib/wsolve.py
reductus/dcsred/__init__.py
reductus/dcsred/dataflow.py
reductus/dcsred/dcs_detector_info.py
reductus/dcsred/dcs_to_JSON.py
reductus/dcsred/dcsdata.py
reductus/dcsred/steps.py
reductus/dcsred/templates/__init__.py
reductus/dcsred/templates/ncnr.dcs.eq.json
reductus/gansred/__init__.py
reductus/gansred/alignfit.py
reductus/gansred/dataflow.py
reductus/gansred/steps.py
reductus/gansred/templates/__init__.py
reductus/gansred/templates/gans.unpolarized.json
reductus/ospecred/FilterableMetaArray.py
reductus/ospecred/MetaArray.py
reductus/ospecred/__init__.py
reductus/ospecred/asterix_filters.py
reductus/ospecred/asterix_loaders.py
reductus/ospecred/dataflow.py
reductus/ospecred/filters.py
reductus/ospecred/he3analyzer.py
reductus/ospecred/magik_filters.py
reductus/ospecred/magik_filters_func.py
reductus/ospecred/magik_loaders.py
reductus/ospecred/xray_loaders.py
reductus/ospecred/templates/__init__.py
reductus-1.0.1.dist-info/LICENSE
reductus-1.0.1.dist-info/METADATA
reductus-1.0.1.dist-info/WHEEL
reductus-1.0.1.dist-info/entry_points.txt
reductus-1.0.1.dist-info/top_level.txt
reductus-1.0.1.dist-info/RECORD
