Metadata-Version: 2.2
Name: reductus
Version: 1.0.1
Summary: Data reduction for neutron scattering
Author-email: Paul Kienzle <paul.kienzle@nist.gov>, Brian Maranville <brian.maranville@nist.gov>
License: Public Domain
Classifier: Development Status :: 5 - Production/Stable
Classifier: Environment :: Console
Classifier: Intended Audience :: Science/Research
Classifier: License :: Public Domain
Classifier: Operating System :: OS Independent
Classifier: Programming Language :: Python
Classifier: Programming Language :: Python :: 3.9
Classifier: Topic :: Scientific/Engineering
Classifier: Topic :: Scientific/Engineering :: Chemistry
Classifier: Topic :: Scientific/Engineering :: Physics
Requires-Python: >=3.9
License-File: LICENSE
Requires-Dist: scipy
Requires-Dist: numpy
Requires-Dist: uncertainties
Requires-Dist: docutils
Requires-Dist: pytz
Provides-Extra: server
Requires-Dist: msgpack; extra == "server"
Requires-Dist: flask; extra == "server"
Requires-Dist: flask-cors; extra == "server"
Requires-Dist: requests; extra == "server"
Provides-Extra: masked-curve-fit
Requires-Dist: numdifftools; extra == "masked-curve-fit"
Provides-Extra: nexus-files
Requires-Dist: h5py; extra == "nexus-files"
Provides-Extra: all
Requires-Dist: msgpack; extra == "all"
Requires-Dist: flask; extra == "all"
Requires-Dist: flask-cors; extra == "all"
Requires-Dist: requests; extra == "all"
Requires-Dist: numdifftools; extra == "all"
Requires-Dist: h5py; extra == "all"
